README.rst
setup.py
docker_executor.egg-info/PKG-INFO
docker_executor.egg-info/SOURCES.txt
docker_executor.egg-info/dependency_links.txt
docker_executor.egg-info/entry_points.txt
docker_executor.egg-info/requires.txt
docker_executor.egg-info/top_level.txt
executor/__init__.py
executor/cli.py
executor/docker.py
executor/net.py
executor/servicediscovery.py
executor/utils.py
utils/pipework